MANIFEST.in
README.md
setup.py
bin/gen_names_sadowski.bat
gen_names_sadowski/__init__.py
gen_names_sadowski/gen_names_sadowski.py
gen_names_sadowski.egg-info/PKG-INFO
gen_names_sadowski.egg-info/SOURCES.txt
gen_names_sadowski.egg-info/dependency_links.txt
gen_names_sadowski.egg-info/requires.txt
gen_names_sadowski.egg-info/top_level.txt