Metadata-Version: 1.0
Name: gen-names-sadowski
Version: 0.1.0
Summary: Generate random names with length
Home-page: https://github.com/krzs13
Author: Krzysztof Sadowski
Author-email: krzysztofsadowski1989@gmail.com
License: UNKNOWN
Keywords: random names
Platform: UNKNOWN
